bluesky_httpserver/__init__.py
bluesky_httpserver/_version.py
bluesky_httpserver/app.py
bluesky_httpserver/authentication.py
bluesky_httpserver/authenticators.py
bluesky_httpserver/config.py
bluesky_httpserver/console_output.py
bluesky_httpserver/core.py
bluesky_httpserver/resources.py
bluesky_httpserver/schemas.py
bluesky_httpserver/server.py
bluesky_httpserver/settings.py
bluesky_httpserver/utils.py
bluesky_httpserver/authorization/__init__.py
bluesky_httpserver/authorization/_defaults.py
bluesky_httpserver/authorization/api_access.py
bluesky_httpserver/authorization/resource_access.py
bluesky_httpserver/config_schemas/__init__.py
bluesky_httpserver/config_schemas/loading.py
bluesky_httpserver/config_schemas/service_configuration.yml
bluesky_httpserver/database/__init__.py
bluesky_httpserver/database/alembic.ini.template
bluesky_httpserver/database/alembic_utils.py
bluesky_httpserver/database/base.py
bluesky_httpserver/database/core.py
bluesky_httpserver/database/orm.py
bluesky_httpserver/database/migrations/env.py
bluesky_httpserver/database/migrations/script.py.mako
bluesky_httpserver/database/migrations/versions/481830dd6c11_initialize.py
bluesky_httpserver/database/migrations/versions/722ff4e4fcc7_add_write_scopes_to_default_roles.py
bluesky_httpserver/routers/__init__.py
bluesky_httpserver/routers/core_api.py
bluesky_httpserver/tests/__init__.py
bluesky_httpserver/tests/conftest.py
bluesky_httpserver/tests/test_access_control.py
bluesky_httpserver/tests/test_access_policies.py
bluesky_httpserver/tests/test_auth_api.py
bluesky_httpserver/tests/test_auth_for_websockets.py
bluesky_httpserver/tests/test_authenticators.py
bluesky_httpserver/tests/test_console_output.py
bluesky_httpserver/tests/test_core_api_fs.py
bluesky_httpserver/tests/test_core_api_main.py
bluesky_httpserver/tests/test_server.py
bluesky_httpserver/tests/test_system_info_socket.py
bluesky_httpserver/tests/test_utils.py
bluesky_httpserver/tests/access_api_server/__init__.py
bluesky_httpserver-0.0.14.dist-info/licenses/AUTHORS.rst
bluesky_httpserver-0.0.14.dist-info/licenses/LICENSE
bluesky_httpserver-0.0.14.dist-info/METADATA
bluesky_httpserver-0.0.14.dist-info/WHEEL
bluesky_httpserver-0.0.14.dist-info/entry_points.txt
bluesky_httpserver-0.0.14.dist-info/top_level.txt
bluesky_httpserver-0.0.14.dist-info/RECORD
