Metadata-Version: 2.4
Name: bluesky-httpserver
Version: 0.0.14
Summary: HTTP Server for communicating with Bluesky Queue Server
Home-page: https://github.com/bluesky/bluesky-httpserver
Author: Brookhaven National Laboratory
Author-email: 
License: BSD (3-clause)
Classifier: Development Status :: 2 - Pre-Alpha
Classifier: Natural Language :: English
Classifier: Programming Language :: Python :: 3
Requires-Python: >=3.7
License-File: LICENSE
License-File: AUTHORS.rst
Requires-Dist: alembic
Requires-Dist: bluesky-queueserver
Requires-Dist: bluesky-queueserver-api
Requires-Dist: fastapi
Requires-Dist: ldap3
Requires-Dist: orjson
Requires-Dist: pamela
Requires-Dist: pydantic
Requires-Dist: pydantic-settings
Requires-Dist: python-jose
Requires-Dist: pyzmq
Requires-Dist: sqlalchemy
Requires-Dist: starlette
Requires-Dist: typing-extensions; python_version < "3.8"
Requires-Dist: uvicorn
Dynamic: author
Dynamic: classifier
Dynamic: description
Dynamic: home-page
Dynamic: license
Dynamic: license-file
Dynamic: requires-dist
Dynamic: requires-python
Dynamic: summary
